Workbook

Sheet Ringkasan
A1: Saloka.id — Ringkasan Progres Fitur
A2: Snapshot 13 Sep 2026; baris Snackbox, Keranjang/Pelacakan Pesanan, DOKU, Biteship, dan modul Komunitas 6.c.xv–xxiv diverifikasi ulang 30 Sep 2026. Angka diperbarui otomatis ketika status diubah di sheet “Pelacak Fitur”.
A4: Fitur | B4: Status keseluruhan | C4: Ringkasan | D4: Halaman / tab yang dilacak | E4: Selesai | F4: Quality Check | G4: Sedang Berjalan | H4: Belum Dimulai | I4: % Selesai | J4: % Selesai atau dalam QC
A5: Halaman Utama & Pencarian | B5: =INDEX('Pelacak Fitur'!$E:$E,MATCH($A5,'Pelacak Fitur'!$D:$D,0)) | C5: =INDEX('Pelacak Fitur'!$F:$F,MATCH($A5,'Pelacak Fitur'!$D:$D,0)) | D5: =COUNTIFS('Pelacak Fitur'!$B:$B,$A5,'Pelacak Fitur'!$C:$C,"<>Fitur") | E5: =COUNTIFS('Pelacak Fitur'!$B:$B,$A5,'Pelacak Fitur'!$C:$C,"<>Fitur",'Pelacak Fitur'!$E:$E,"Selesai") | F5: =COUNTIFS('Pelacak Fitur'!$B:$B,$A5,'Pelacak Fitur'!$C:$C,"<>Fitur",'Pelacak Fitur'!$E:$E,"Quality Check") | G5: =COUNTIFS('Pelacak Fitur'!$B:$B,$A5,'Pelacak Fitur'!$C:$C,"<>Fitur",'Pelacak Fitur'!$E:$E,"Sedang Berjalan") | H5: =COUNTIFS('Pelacak Fitur'!$B:$B,$A5,'Pelacak Fitur'!$C:$C,"<>Fitur",'Pelacak Fitur'!$E:$E,"Belum Dimulai") | I5: =IF(D5=0,"",E5/D5) | J5: =IF(D5=0,"",(E5+F5)/D5)
A6: Akun & Identitas | B6: =INDEX('Pelacak Fitur'!$E:$E,MATCH($A6,'Pelacak Fitur'!$D:$D,0)) | C6: =INDEX('Pelacak Fitur'!$F:$F,MATCH($A6,'Pelacak Fitur'!$D:$D,0)) | D6: =COUNTIFS('Pelacak Fitur'!$B:$B,$A6,'Pelacak Fitur'!$C:$C,"<>Fitur") | E6: =COUNTIFS('Pelacak Fitur'!$B:$B,$A6,'Pelacak Fitur'!$C:$C,"<>Fitur",'Pelacak Fitur'!$E:$E,"Selesai") | F6: =COUNTIFS('Pelacak Fitur'!$B:$B,$A6,'Pelacak Fitur'!$C:$C,"<>Fitur",'Pelacak Fitur'!$E:$E,"Quality Check") | G6: =COUNTIFS('Pelacak Fitur'!$B:$B,$A6,'Pelacak Fitur'!$C:$C,"<>Fitur",'Pelacak Fitur'!$E:$E,"Sedang Berjalan") | H6: =COUNTIFS('Pelacak Fitur'!$B:$B,$A6,'Pelacak Fitur'!$C:$C,"<>Fitur",'Pelacak Fitur'!$E:$E,"Belum Dimulai") | I6: =IF(D6=0,"",E6/D6) | J6: =IF(D6=0,"",(E6+F6)/D6)
A7: Marketplace (Produk) | B7: =INDEX('Pelacak Fitur'!$E:$E,MATCH($A7,'Pelacak Fitur'!$D:$D,0)) | C7: =INDEX('Pelacak Fitur'!$F:$F,MATCH($A7,'Pelacak Fitur'!$D:$D,0)) | D7: =COUNTIFS('Pelacak Fitur'!$B:$B,$A7,'Pelacak Fitur'!$C:$C,"<>Fitur") | E7: =COUNTIFS('Pelacak Fitur'!$B:$B,$A7,'Pelacak Fitur'!$C:$C,"<>Fitur",'Pelacak Fitur'!$E:$E,"Selesai") | F7: =COUNTIFS('Pelacak Fitur'!$B:$B,$A7,'Pelacak Fitur'!$C:$C,"<>Fitur",'Pelacak Fitur'!$E:$E,"Quality Check") | G7: =COUNTIFS('Pelacak Fitur'!$B:$B,$A7,'Pelacak Fitur'!$C:$C,"<>Fitur",'Pelacak Fitur'!$E:$E,"Sedang Berjalan") | H7: =COUNTIFS('Pelacak Fitur'!$B:$B,$A7,'Pelacak Fitur'!$C:$C,"<>Fitur",'Pelacak Fitur'!$E:$E,"Belum Dimulai") | I7: =IF(D7=0,"",E7/D7) | J7: =IF(D7=0,"",(E7+F7)/D7)
A8: Jasa | B8: =INDEX('Pelacak Fitur'!$E:$E,MATCH($A8,'Pelacak Fitur'!$D:$D,0)) | C8: =INDEX('Pelacak Fitur'!$F:$F,MATCH($A8,'Pelacak Fitur'!$D:$D,0)) | D8: =COUNTIFS('Pelacak Fitur'!$B:$B,$A8,'Pelacak Fitur'!$C:$C,"<>Fitur") | E8: =COUNTIFS('Pelacak Fitur'!$B:$B,$A8,'Pelacak Fitur'!$C:$C,"<>Fitur",'Pelacak Fitur'!$E:$E,"Selesai") | F8: =COUNTIFS('Pelacak Fitur'!$B:$B,$A8,'Pelacak Fitur'!$C:$C,"<>Fitur",'Pelacak Fitur'!$E:$E,"Quality Check") | G8: =COUNTIFS('Pelacak Fitur'!$B:$B,$A8,'Pelacak Fitur'!$C:$C,"<>Fitur",'Pelacak Fitur'!$E:$E,"Sedang Berjalan") | H8: =COUNTIFS('Pelacak Fitur'!$B:$B,$A8,'Pelacak Fitur'!$C:$C,"<>Fitur",'Pelacak Fitur'!$E:$E,"Belum Dimulai") | I8: =IF(D8=0,"",E8/D8) | J8: =IF(D8=0,"",(E8+F8)/D8)
A9: Snackbox | B9: =INDEX('Pelacak Fitur'!$E:$E,MATCH($A9,'Pelacak Fitur'!$D:$D,0)) | C9: =INDEX('Pelacak Fitur'!$F:$F,MATCH($A9,'Pelacak Fitur'!$D:$D,0)) | D9: =COUNTIFS('Pelacak Fitur'!$B:$B,$A9,'Pelacak Fitur'!$C:$C,"<>Fitur") | E9: =COUNTIFS('Pelacak Fitur'!$B:$B,$A9,'Pelacak Fitur'!$C:$C,"<>Fitur",'Pelacak Fitur'!$E:$E,"Selesai") | F9: =COUNTIFS('Pelacak Fitur'!$B:$B,$A9,'Pelacak Fitur'!$C:$C,"<>Fitur",'Pelacak Fitur'!$E:$E,"Quality Check") | G9: =COUNTIFS('Pelacak Fitur'!$B:$B,$A9,'Pelacak Fitur'!$C:$C,"<>Fitur",'Pelacak Fitur'!$E:$E,"Sedang Berjalan") | H9: =COUNTIFS('Pelacak Fitur'!$B:$B,$A9,'Pelacak Fitur'!$C:$C,"<>Fitur",'Pelacak Fitur'!$E:$E,"Belum Dimulai") | I9: =IF(D9=0,"",E9/D9) | J9: =IF(D9=0,"",(E9+F9)/D9)
A10: Komunitas | B10: =INDEX('Pelacak Fitur'!$E:$E,MATCH($A10,'Pelacak Fitur'!$D:$D,0)) | C10: =INDEX('Pelacak Fitur'!$F:$F,MATCH($A10,'Pelacak Fitur'!$D:$D,0)) | D10: =COUNTIFS('Pelacak Fitur'!$B:$B,$A10,'Pelacak Fitur'!$C:$C,"<>Fitur") | E10: =COUNTIFS('Pelacak Fitur'!$B:$B,$A10,'Pelacak Fitur'!$C:$C,"<>Fitur",'Pelacak Fitur'!$E:$E,"Selesai") | F10: =COUNTIFS('Pelacak Fitur'!$B:$B,$A10,'Pelacak Fitur'!$C:$C,"<>Fitur",'Pelacak Fitur'!$E:$E,"Quality Check") | G10: =COUNTIFS('Pelacak Fitur'!$B:$B,$A10,'Pelacak Fitur'!$C:$C,"<>Fitur",'Pelacak Fitur'!$E:$E,"Sedang Berjalan") | H10: =COUNTIFS('Pelacak Fitur'!$B:$B,$A10,'Pelacak Fitur'!$C:$C,"<>Fitur",'Pelacak Fitur'!$E:$E,"Belum Dimulai") | I10: =IF(D10=0,"",E10/D10) | J10: =IF(D10=0,"",(E10+F10)/D10)
A11: Pembayaran, Wallet & Koin | B11: =INDEX('Pelacak Fitur'!$E:$E,MATCH($A11,'Pelacak Fitur'!$D:$D,0)) | C11: =INDEX('Pelacak Fitur'!$F:$F,MATCH($A11,'Pelacak Fitur'!$D:$D,0)) | D11: =COUNTIFS('Pelacak Fitur'!$B:$B,$A11,'Pelacak Fitur'!$C:$C,"<>Fitur") | E11: =COUNTIFS('Pelacak Fitur'!$B:$B,$A11,'Pelacak Fitur'!$C:$C,"<>Fitur",'Pelacak Fitur'!$E:$E,"Selesai") | F11: =COUNTIFS('Pelacak Fitur'!$B:$B,$A11,'Pelacak Fitur'!$C:$C,"<>Fitur",'Pelacak Fitur'!$E:$E,"Quality Check") | G11: =COUNTIFS('Pelacak Fitur'!$B:$B,$A11,'Pelacak Fitur'!$C:$C,"<>Fitur",'Pelacak Fitur'!$E:$E,"Sedang Berjalan") | H11: =COUNTIFS('Pelacak Fitur'!$B:$B,$A11,'Pelacak Fitur'!$C:$C,"<>Fitur",'Pelacak Fitur'!$E:$E,"Belum Dimulai") | I11: =IF(D11=0,"",E11/D11) | J11: =IF(D11=0,"",(E11+F11)/D11)
A12: Alat Merchant & Storefront | B12: =INDEX('Pelacak Fitur'!$E:$E,MATCH($A12,'Pelacak Fitur'!$D:$D,0)) | C12: =INDEX('Pelacak Fitur'!$F:$F,MATCH($A12,'Pelacak Fitur'!$D:$D,0)) | D12: =COUNTIFS('Pelacak Fitur'!$B:$B,$A12,'Pelacak Fitur'!$C:$C,"<>Fitur") | E12: =COUNTIFS('Pelacak Fitur'!$B:$B,$A12,'Pelacak Fitur'!$C:$C,"<>Fitur",'Pelacak Fitur'!$E:$E,"Selesai") | F12: =COUNTIFS('Pelacak Fitur'!$B:$B,$A12,'Pelacak Fitur'!$C:$C,"<>Fitur",'Pelacak Fitur'!$E:$E,"Quality Check") | G12: =COUNTIFS('Pelacak Fitur'!$B:$B,$A12,'Pelacak Fitur'!$C:$C,"<>Fitur",'Pelacak Fitur'!$E:$E,"Sedang Berjalan") | H12: =COUNTIFS('Pelacak Fitur'!$B:$B,$A12,'Pelacak Fitur'!$C:$C,"<>Fitur",'Pelacak Fitur'!$E:$E,"Belum Dimulai") | I12: =IF(D12=0,"",E12/D12) | J12: =IF(D12=0,"",(E12+F12)/D12)
A13: Affiliate | B13: =INDEX('Pelacak Fitur'!$E:$E,MATCH($A13,'Pelacak Fitur'!$D:$D,0)) | C13: =INDEX('Pelacak Fitur'!$F:$F,MATCH($A13,'Pelacak Fitur'!$D:$D,0)) | D13: =COUNTIFS('Pelacak Fitur'!$B:$B,$A13,'Pelacak Fitur'!$C:$C,"<>Fitur") | E13: =COUNTIFS('Pelacak Fitur'!$B:$B,$A13,'Pelacak Fitur'!$C:$C,"<>Fitur",'Pelacak Fitur'!$E:$E,"Selesai") | F13: =COUNTIFS('Pelacak Fitur'!$B:$B,$A13,'Pelacak Fitur'!$C:$C,"<>Fitur",'Pelacak Fitur'!$E:$E,"Quality Check") | G13: =COUNTIFS('Pelacak Fitur'!$B:$B,$A13,'Pelacak Fitur'!$C:$C,"<>Fitur",'Pelacak Fitur'!$E:$E,"Sedang Berjalan") | H13: =COUNTIFS('Pelacak Fitur'!$B:$B,$A13,'Pelacak Fitur'!$C:$C,"<>Fitur",'Pelacak Fitur'!$E:$E,"Belum Dimulai") | I13: =IF(D13=0,"",E13/D13) | J13: =IF(D13=0,"",(E13+F13)/D13)
A14: Academy (LMS) | B14: =INDEX('Pelacak Fitur'!$E:$E,MATCH($A14,'Pelacak Fitur'!$D:$D,0)) | C14: =INDEX('Pelacak Fitur'!$F:$F,MATCH($A14,'Pelacak Fitur'!$D:$D,0)) | D14: =COUNTIFS('Pelacak Fitur'!$B:$B,$A14,'Pelacak Fitur'!$C:$C,"<>Fitur") | E14: =COUNTIFS('Pelacak Fitur'!$B:$B,$A14,'Pelacak Fitur'!$C:$C,"<>Fitur",'Pelacak Fitur'!$E:$E,"Selesai") | F14: =COUNTIFS('Pelacak Fitur'!$B:$B,$A14,'Pelacak Fitur'!$C:$C,"<>Fitur",'Pelacak Fitur'!$E:$E,"Quality Check") | G14: =COUNTIFS('Pelacak Fitur'!$B:$B,$A14,'Pelacak Fitur'!$C:$C,"<>Fitur",'Pelacak Fitur'!$E:$E,"Sedang Berjalan") | H14: =COUNTIFS('Pelacak Fitur'!$B:$B,$A14,'Pelacak Fitur'!$C:$C,"<>Fitur",'Pelacak Fitur'!$E:$E,"Belum Dimulai") | I14: =IF(D14=0,"",E14/D14) | J14: =IF(D14=0,"",(E14+F14)/D14)
A15: Chat & Layanan Pelanggan (CS) | B15: =INDEX('Pelacak Fitur'!$E:$E,MATCH($A15,'Pelacak Fitur'!$D:$D,0)) | C15: =INDEX('Pelacak Fitur'!$F:$F,MATCH($A15,'Pelacak Fitur'!$D:$D,0)) | D15: =COUNTIFS('Pelacak Fitur'!$B:$B,$A15,'Pelacak Fitur'!$C:$C,"<>Fitur") | E15: =COUNTIFS('Pelacak Fitur'!$B:$B,$A15,'Pelacak Fitur'!$C:$C,"<>Fitur",'Pelacak Fitur'!$E:$E,"Selesai") | F15: =COUNTIFS('Pelacak Fitur'!$B:$B,$A15,'Pelacak Fitur'!$C:$C,"<>Fitur",'Pelacak Fitur'!$E:$E,"Quality Check") | G15: =COUNTIFS('Pelacak Fitur'!$B:$B,$A15,'Pelacak Fitur'!$C:$C,"<>Fitur",'Pelacak Fitur'!$E:$E,"Sedang Berjalan") | H15: =COUNTIFS('Pelacak Fitur'!$B:$B,$A15,'Pelacak Fitur'!$C:$C,"<>Fitur",'Pelacak Fitur'!$E:$E,"Belum Dimulai") | I15: =IF(D15=0,"",E15/D15) | J15: =IF(D15=0,"",(E15+F15)/D15)
A16: Admin CMS (Platform) | B16: =INDEX('Pelacak Fitur'!$E:$E,MATCH($A16,'Pelacak Fitur'!$D:$D,0)) | C16: =INDEX('Pelacak Fitur'!$F:$F,MATCH($A16,'Pelacak Fitur'!$D:$D,0)) | D16: =COUNTIFS('Pelacak Fitur'!$B:$B,$A16,'Pelacak Fitur'!$C:$C,"<>Fitur") | E16: =COUNTIFS('Pelacak Fitur'!$B:$B,$A16,'Pelacak Fitur'!$C:$C,"<>Fitur",'Pelacak Fitur'!$E:$E,"Selesai") | F16: =COUNTIFS('Pelacak Fitur'!$B:$B,$A16,'Pelacak Fitur'!$C:$C,"<>Fitur",'Pelacak Fitur'!$E:$E,"Quality Check") | G16: =COUNTIFS('Pelacak Fitur'!$B:$B,$A16,'Pelacak Fitur'!$C:$C,"<>Fitur",'Pelacak Fitur'!$E:$E,"Sedang Berjalan") | H16: =COUNTIFS('Pelacak Fitur'!$B:$B,$A16,'Pelacak Fitur'!$C:$C,"<>Fitur",'Pelacak Fitur'!$E:$E,"Belum Dimulai") | I16: =IF(D16=0,"",E16/D16) | J16: =IF(D16=0,"",(E16+F16)/D16)
A17: Halaman Legal | B17: =INDEX('Pelacak Fitur'!$E:$E,MATCH($A17,'Pelacak Fitur'!$D:$D,0)) | C17: =INDEX('Pelacak Fitur'!$F:$F,MATCH($A17,'Pelacak Fitur'!$D:$D,0)) | D17: =COUNTIFS('Pelacak Fitur'!$B:$B,$A17,'Pelacak Fitur'!$C:$C,"<>Fitur") | E17: =COUNTIFS('Pelacak Fitur'!$B:$B,$A17,'Pelacak Fitur'!$C:$C,"<>Fitur",'Pelacak Fitur'!$E:$E,"Selesai") | F17: =COUNTIFS('Pelacak Fitur'!$B:$B,$A17,'Pelacak Fitur'!$C:$C,"<>Fitur",'Pelacak Fitur'!$E:$E,"Quality Check") | G17: =COUNTIFS('Pelacak Fitur'!$B:$B,$A17,'Pelacak Fitur'!$C:$C,"<>Fitur",'Pelacak Fitur'!$E:$E,"Sedang Berjalan") | H17: =COUNTIFS('Pelacak Fitur'!$B:$B,$A17,'Pelacak Fitur'!$C:$C,"<>Fitur",'Pelacak Fitur'!$E:$E,"Belum Dimulai") | I17: =IF(D17=0,"",E17/D17) | J17: =IF(D17=0,"",(E17+F17)/D17)
A18: TOTAL | D18: =SUM(D5:D17) | E18: =SUM(E5:E17) | F18: =SUM(F5:F17) | G18: =SUM(G5:G17) | H18: =SUM(H5:H17) | I18: =IF(D18=0,"",E18/D18) | J18: =IF(D18=0,"",(E18+F18)/D18)

Sheet Pelacak Fitur
A1: FITUR & HALAMAN | G1: DETAIL | P1: PELACAKAN | T1: ITERASI 1 · S.D. 22 AGU 2026 (HANYA PERBAIKAN BESAR) | X1: ITERASI 2 · 23–31 AGU 2026 | AB1: ITERASI 3 · 1–6 SEP 2026 (MINGGU A) | AF1: ITERASI 4 · 7–13 SEP 2026 (MINGGU B)
A2: No. | B2: Fitur | C2: Level | D2: Nama | E2: Status | F2: Alasan status (hasil inferensi) | G2: Link (saloka.id) | H2: Siapa yang bisa akses | I2: Fungsi | J2: Data yang ditampilkan / disimpan | K2: Tabel database | L2: Server action & API endpoint | M2: File kode utama | N2: Roadmap Sept 2026 | O2: Kekurangan / isu terbuka | P2: Pertama dibuat (git) | Q2: Terakhir diubah (git) | R2: PIC | S2: Target tanggal | T2: Bug ditemukan | U2: Tanggal ditemukan | V2: Perbaikan | W2: Tanggal perbaikan | X2: Bug ditemukan | Y2: Tanggal ditemukan | Z2: Perbaikan | AA2: Tanggal perbaikan | AB2: Bug ditemukan | AC2: Tanggal ditemukan | AD2: Perbaikan | AE2: Tanggal perbaikan | AF2: Bug ditemukan | AG2: Tanggal ditemukan | AH2: Perbaikan | AI2: Tanggal perbaikan
A3: 1 | B3: Halaman Utama & Pencarian | C3: Fitur | D3: Halaman Utama & Pencarian | E3: Quality Check | F3: Berjalan dengan data asli; halaman utama diubah 13 Sep; penyempurnaan notifikasi masih ada di roadmap.
A4: 1.a | B4: Halaman Utama & Pencarian | C4: Halaman | D4: Halaman Utama | E4: Quality Check | F4: Diubah 13 Sep; kartu komunitas contoh masih dipakai sebagai cadangan. | G4: https://saloka.id/ | H4: Semua orang (publik) | I4: Halaman masuk utama: carousel banner promo, sorotan produk dan jasa, kartu komunitas, ikon aksi cepat. | J4: Banner promo aktif, produk, jasa, komunitas (dan komunitas yang sudah diikuti pengunjung) | K4: LandingBanner, Product, Service, Community, CommunityMembership, User | L4: landing.getActiveBanners; products.getProducts; services.getServicesAction; community.getIndukCommunities; auth.getCurrentUser | M4: src/app/page.tsx; src/app/components/HomeExplorer.tsx; src/app/components/BannerCarousel.tsx | O4: Menampilkan 3 kartu komunitas contoh yang di-hardcode (comm-dummy-1..3) jika tidak ada komunitas yang termuat. | P4: 2026-05-23 | Q4: 2026-09-13
A5: 1.b | B5: Halaman Utama & Pencarian | C5: Komponen | D5: Pencarian global (navbar) | E5: Selesai | F5: Data asli; dirilis 25–31 Agu; tidak ada perbaikan bug sejak itu. | G5: Navbar di setiap halaman → /market?q=… , /jasa?search=… | H5: Semua orang | I5: Pencarian instan dengan autocomplete untuk produk, jasa, dan komunitas, dengan rekomendasi jika tidak ada hasil. | J5: Produk, jasa, komunitas yang cocok dengan kata kunci | K5: Product, Service, Community | L5: search.searchGlobalAction | M5: src/app/actions/search.ts; src/app/components/HeaderNavigation.tsx | P5: 2026-08-29 | Q5: 2026-08-29
A6: 1.c | B6: Halaman Utama & Pencarian | C6: Komponen | D6: Lonceng notifikasi | E6: Quality Check | F6: Berjalan dengan data asli; roadmap Minggu B masih mencantumkan penyempurnaan notifikasi. | G6: Navbar (setelah login) | H6: Pengguna yang sudah login | I6: Notifikasi dalam aplikasi (update pesanan, aktivitas komunitas, balasan). | J6: Notifikasi per pengguna, sudah/belum dibaca | K6: Notification | L6: GET/POST /api/notifications | M6: src/app/components/NotificationBell.tsx; src/app/api/notifications/route.ts | N6: Minggu B: menyempurnakan sistem notifikasi | P6: 2026-05-31 | Q6: 2026-08-29
A7: 2 | B7: Akun & Identitas | C7: Fitur | D7: Akun & Identitas | E7: Quality Check | F7: Keamanan login dan atribusi referral dibangun ulang 13 Sep; KYC masih punya jalur uji coba/bypass.
A8: 2.a | B8: Akun & Identitas | C8: Halaman | D8: Login & Daftar | E8: Quality Check | F8: Rate limiting dibangun ulang 13 Sep; perlu diuji ulang. | G8: https://saloka.id/auth?tab=login | H8: Semua orang | I8: Login & pendaftaran dengan email/password (password di-hash bcrypt), login Google, percobaan login dibatasi (rate limit); logout menghapus cookie sesi di semua domain Saloka. | J8: Kredensial akun, cookie sesi, percobaan login gagal | K8: User, Wallet, RateLimitAttempt, AuditLog | L8: auth.login / register / logout; /api/auth/google/callback; /api/auth/check-username; /api/auth/logout; /api/auth/clear-cookies | M8: src/app/auth/page.tsx; src/components/AuthForm.tsx; src/app/actions/auth.ts; src/lib/rate-limit.ts | N8: Jalur paralel: Sistem Verifikasi, ISO 27001 | P8: 2026-05-30 | Q8: 2026-09-13 | T8: Logout meninggalkan cookie sesi di domain Saloka lain (pengguna tetap login) | U8: — | V8: Route logout menghapus cookie di semua domain (15dc8d4, ce7be98, fcf422c) | W8: 2026-07-22 | AF8: Rate limit login ter-reset per instance server (risiko brute-force) | AG8: — | AH8: Rate limiting disimpan di database (1c4c28b) | AI8: 2026-09-13
A9: 2.b | B9: Akun & Identitas | C9: Halaman | D9: Pilih peran akun | E9: Selesai | F9: Tidak berubah sejak 18 Jul; tidak ditemukan masalah terbuka di kode. | G9: https://saloka.id/auth/select-role | H9: Pengguna yang baru mendaftar | I9: Memilih jenis akun setelah mendaftar. | J9: Peran pengguna | K9: User | L9: auth.selectUserRole | M9: src/app/auth/select-role/page.tsx | P9: 2026-07-18 | Q9: 2026-07-18
A10: 2.c | B10: Akun & Identitas | C10: Halaman | D10: Lupa password | E10: Quality Check | F10: Dibuat 1 Sep; belum ada catatan QA. | G10: https://saloka.id/forgot-password | H10: Semua orang | I10: Reset password dengan kode sekali pakai. | J10: Kode reset, hash password baru | K10: User | L10: auth.requestPasswordReset; auth.resetPasswordWithOtp | M10: src/app/forgot-password/page.tsx | P10: 2026-09-01 | Q10: 2026-09-01
A11: 2.d | B11: Akun & Identitas | C11: Halaman | D11: Onboarding | E11: Quality Check | F11: Terakhir diubah 1 Sep; belum ada catatan QA. | G11: https://saloka.id/onboarding | H11: Pengguna yang sudah login tetapi belum menyelesaikan pengaturan awal | I11: Pengaturan bertahap: verifikasi nomor HP/email dengan OTP, tambah alamat, buat subdomain toko (merchant). | J11: Verifikasi HP & email, alamat, subdomain | K11: User | L11: auth.saveOnboardingData, checkSubdomainAvailability, sendPhoneVerificationOtp, verifyPhoneOtp, sendEmailVerificationOtp, verifyEmailOtp, checkWhatsAppUnique | M11: src/app/onboarding/page.tsx; src/app/components/OnboardingGuard.tsx | P11: 2026-06-07 | Q11: 2026-09-01
A12: 2.e | B12: Akun & Identitas | C12: Halaman | D12: Pengaturan akun | E12: Quality Check | F12: Diubah 9 Sep. | G12: https://saloka.id/settings | H12: Pengguna yang sudah login | I12: Pusat pengaturan akun dengan 8 tab (di bawah). | J12: Profil, keamanan, KYC, referral, alamat, WhatsApp gateway, preferensi notifikasi & tampilan | K12: User, Wallet | L12: auth.updateUsernameAction, getReferralInfo; wallet-affiliate.updateUserSettingsAction, getWaLogsAction; /api/kyc/didit, /api/kyc/status, /api/kyc/simulate; /api/upload | M12: src/app/settings/page.tsx | P12: 2026-06-09 | Q12: 2026-09-09
A13: 2.e.i | B13: Akun & Identitas | C13: Tab | D13: Profil & Biodata | E13: Quality Check | F13: Bagian dari Pengaturan akun (diubah 9 Sep). | G13: https://saloka.id/settings (tab dipilih di dalam halaman) | H13: Pengguna yang sudah login | I13: Nama, foto (upload), dan bio. | M13: src/app/settings/page.tsx | P13: 2026-06-09 | Q13: 2026-09-09
A14: 2.e.ii | B14: Akun & Identitas | C14: Tab | D14: Akun & Keamanan | E14: Quality Check | F14: Bagian dari Pengaturan akun (diubah 9 Sep). | G14: https://saloka.id/settings (tab dipilih di dalam halaman) | H14: Pengguna yang sudah login | I14: Username, password, nomor HP, dan email. | M14: src/app/settings/page.tsx | P14: 2026-06-09 | Q14: 2026-09-09
A15: 2.e.iii | B15: Akun & Identitas | C15: Tab | D15: Verifikasi Identitas (KYC) | E15: Quality Check | F15: Bagian dari Pengaturan akun (diubah 9 Sep). | G15: https://saloka.id/settings (tab dipilih di dalam halaman) | H15: Pengguna yang sudah login | I15: Memulai verifikasi identitas dengan Didit dan melihat statusnya. | M15: src/app/settings/page.tsx | O15: Pemanggilan KYC “simulate” masih terpasang di halaman ini (/api/kyc/simulate). | P15: 2026-06-09 | Q15: 2026-09-09
A16: 2.e.iv | B16: Akun & Identitas | C16: Tab | D16: Referral & Coin | E16: Quality Check | F16: Bagian dari Pengaturan akun (diubah 9 Sep). | G16: https://saloka.id/settings (tab dipilih di dalam halaman) | H16: Pengguna yang sudah login | I16: Link referral pribadi dan ringkasan koin. | M16: src/app/settings/page.tsx | P16: 2026-06-09 | Q16: 2026-09-09
A17: 2.e.v | B17: Akun & Identitas | C17: Tab | D17: Buku Alamat | E17: Quality Check | F17: Bagian dari Pengaturan akun (diubah 9 Sep). | G17: https://saloka.id/settings (tab dipilih di dalam halaman) | H17: Pengguna yang sudah login | I17: Alamat pengiriman yang tersimpan. | M17: src/app/settings/page.tsx | P17: 2026-06-09 | Q17: 2026-09-09
A18: 2.e.vi | B18: Akun & Identitas | C18: Tab | D18: Integrasi & WA Gateway | E18: Quality Check | F18: Bagian dari Pengaturan akun (diubah 9 Sep). | G18: https://saloka.id/settings (tab dipilih di dalam halaman) | H18: Pengguna yang sudah login | I18: Pengaturan WhatsApp gateway dan log pesan. | M18: src/app/settings/page.tsx | P18: 2026-06-09 | Q18: 2026-09-09
A19: 2.e.vii | B19: Akun & Identitas | C19: Tab | D19: Notifikasi | E19: Quality Check | F19: Bagian dari Pengaturan akun (diubah 9 Sep). | G19: https://saloka.id/settings (tab dipilih di dalam halaman) | H19: Pengguna yang sudah login | I19: Notifikasi apa saja yang diterima pengguna. | M19: src/app/settings/page.tsx | P19: 2026-06-09 | Q19: 2026-09-09
A20: 2.e.viii | B20: Akun & Identitas | C20: Tab | D20: Preferensi Tampilan | E20: Quality Check | F20: Bagian dari Pengaturan akun (diubah 9 Sep). | G20: https://saloka.id/settings (tab dipilih di dalam halaman) | H20: Pengguna yang sudah login | I20: Preferensi tampilan. | M20: src/app/settings/page.tsx | P20: 2026-06-09 | Q20: 2026-09-09
A21: 2.f | B21: Akun & Identitas | C21: Halaman | D21: Profil publik | E21: Quality Check | F21: Stabil sejak 29 Agu, tetapi ada tombol bypass KYC untuk uji coba di sini. | G21: https://saloka.id/profile/[user-id] | H21: Semua orang (pemilik melihat lebih banyak) | I21: Profil publik / mini storefront: produk, keanggotaan komunitas, total komisi, tombol kontak & bagikan. Link referral mengarah ke sini. | J21: Profil, produk, komunitas & peran, statistik affiliate, ringkasan wallet (pemilik) | K21: User, Order, Wallet, AffiliateReferral, CommunityMembership | L21: DataStore.getUserCommunitiesWithRoles, getAffiliateStats, getWalletByUserId; /api/kyc/didit | M21: src/app/profile/[id]/page.tsx; src/app/profile/[id]/ProfileViewerClient.tsx | O21: Tombol bypass KYC ditambahkan untuk uji coba (18 Jul): pastikan tersembunyi di production. | P21: 2026-05-30 | Q21: 2026-08-29
A22: 2.g | B22: Akun & Identitas | C22: Halaman | D22: Callback verifikasi KYC | E22: Quality Check | F22: Perbaikan keandalan di-commit 9 Sep; route uji coba masih ada. | G22: https://saloka.id/kyc/callback | H22: Pengguna yang kembali dari Didit | I22: Halaman setelah pengecekan identitas Didit: sedang diproses / berhasil / sedang ditinjau, lalu otomatis dialihkan. | J22: Status KYC per pengguna | K22: User (kycStatus) | L22: /api/kyc/didit; /api/kyc/status; /api/didit/webhook; /api/kyc/simulate | M22: src/app/kyc/callback/page.tsx; src/app/api/didit/webhook/route.ts | N22: Jalur paralel: Sistem Verifikasi | O22: Route uji coba /api/kyc/simulate masih ada; submitKycAction bisa menyetujui KYC tanpa pengecekan asli (tidak terhubung ke UI tetapi masih bisa dipanggil), ditunda ke Phase 6. | P22: 2026-06-20 | Q22: 2026-06-20 | T22: 1. Signature webhook Didit gagal, hasil KYC tidak pernah diterima 2. KYC crash karena field database hilang / error batas kredit Didit | U22: 1. — 2. — | V22: 1. Upgrade ke Didit V3 API, signature diperbaiki (b1d68d9) 2. Field ditambahkan, error ditangani (7a4a322) | W22: 1. 2026-07-11 2. 2026-07-18
A23: 2.h | B23: Akun & Identitas | C23: Alur | D23: Link pendek referral | E23: Quality Check | F23: Atribusi diperbaiki 13 Sep; perlu diuji ulang. | G23: https://saloka.id/ref/[username] | H23: Semua orang | I23: Mengarahkan pengunjung ke profil pemberi referral (atau ke produk, untuk link affiliate lama) dan menyimpan cookie referral first-touch selama 30 hari. | J23: Cookie referral, pelacakan klik | K23: User, AffiliateReferral | L23: src/app/ref/[slug]/route.ts; affiliate-extra.trackAffiliateClick | M23: src/app/ref/[slug]/route.ts | P23: 2026-09-13 | Q23: 2026-09-13 | AF23: Atribusi referral rusak (pengguna baru tidak terhubung ke pemberi referral) | AG23: — | AH23: Atribusi diperbaiki (1c4c28b) | AI23: 2026-09-13
A24: 3 | B24: Marketplace (Produk) | C24: Fitur | D24: Marketplace (Produk) | E24: Sedang Berjalan | F24: Penjelajahan & halaman produk berjalan; alur pesanan → pembayaran → pengiriman adalah pekerjaan Minggu C dan belum selesai.
A25: 3.a | B25: Marketplace (Produk) | C25: Halaman | D25: Daftar produk Marketplace | E25: Quality Check | F25: Tata letak mobile diperbaiki 1 Sep. | G25: https://saloka.id/market | H25: Semua orang | I25: Katalog produk dengan pencarian, filter kategori, dan urutan. | J25: Produk & info merchant | K25: Product, User | L25: products.getProducts | M25: src/app/market/page.tsx; src/app/market/ProductListGrid.tsx | P25: 2026-05-30 | Q25: 2026-09-01 | T25: Daftar produk crash pada beberapa pencarian (field kosong / indeks negatif) | U25: — | V25: Pencarian & grid dibuat null-safe (25a6964, 5677ae8) | W25: 2026-06-21 | AB25: Tata letak mobile melebihi layar | AC25: — | AD25: Tata letak mobile & padding header diperbaiki (24fa1ed) | AE25: 2026-09-01
A26: 3.b | B26: Marketplace (Produk) | C26: Halaman | D26: Detail produk | E26: Quality Check | F26: Didesain ulang 12 Sep (varian, sticky buy box). | G26: https://saloka.id/market/product/[product-id] | H26: Semua orang (membeli perlu login) | I26: Halaman produk: galeri foto, varian, sticky buy box, tab deskripsi/ulasan, ulasan, chat dengan penjual. | J26: Produk, varian, stok, ulasan | K26: Product, ProductReview, User, Notification | L26: products.getProductById; reviews.createReview, getProductReviews; /api/products/[id]/reviews-check | M26: src/app/market/product/[id]/ProductDetailView.tsx; src/lib/product-variants.ts | O26: Varian disimpan sebagai JSON tersembunyi di dalam deskripsi produk, bukan di tabel tersendiri. | P26: 2026-09-12 | Q26: 2026-09-12
A27: 3.c | B27: Marketplace (Produk) | C27: Halaman | D27: Keranjang & Checkout | E27: Sedang Berjalan | F27: Checkout berjalan; Snackbox kini digabung ke payload pesanan yang sama. Diverifikasi ulang 30 Sep. | G27: https://saloka.id/cart | H27: Semua orang (checkout perlu login) | I27: Keranjang bersama untuk Marketplace dan Snackbox: alamat, tarif kurir (Biteship), rincian biaya, bayar dengan DOKU (QRIS / virtual account) atau wallet; membuat pesanan. | J27: Isi keranjang (browser), ongkos kirim, pesanan, status pembayaran | K27: Order, OrderItem, OrderTracking, Product, Wallet, WalletTransaction, AffiliateReferral, Notification | L27: wallet-affiliate.checkoutCart, getActivePaymentMethods; /api/shipping/destination, /api/shipping/calculate; /api/doku/direct, /api/doku/verify; /api/midtrans/verify (legacy) | M27: src/app/cart/page.tsx; src/components/DokuDirectPaymentModal.tsx | N27: Minggu C (14–20 Sep): alur pesanan → pembayaran → pengiriman | O27: Jalur Midtrans/Komerce dan tombol bypass sandbox sudah dihapus. Sisa: pembagian komisi affiliate 60/10/10/20 masih hardcoded di kode; pelacakan pengiriman belum otomatis. | P27: 2026-05-30 | Q27: 2026-09-12 | T27: 1. Tamu bisa masuk ke checkout tanpa login 2. Total checkout menyembunyikan biaya admin/layanan 3. Pembuatan pesanan gagal saat koneksi database lambat | U27: 1. — 2. — 3. — | V27: 1. Wajib login sebelum checkout + banner untuk tamu (a1b5254) 2. Rincian biaya ditampilkan di total (527f891) 3. Timeout koneksi diperpanjang + pencatatan error (bd4a4cb, 86a6148) | W27: 1. 2026-08-15 2. 2026-08-15 3. 2026-08-15 | AF27: Menutup modal pembayaran membuka halaman 404 | AG27: — | AH27: Penutupan modal ditangani (cb6ff56) | AI27: 2026-09-12
A28: 3.d | B28: Marketplace (Produk) | C28: Halaman | D28: Pesanan saya | E28: Quality Check | F28: Tampilan diperbarui 12 Sep. | G28: https://saloka.id/orders | H28: Pembeli yang sudah login | I28: Daftar pesanan pembeli dengan badge status. | J28: Pesanan & status | K28: Order | L28: orders.getMyOrders | M28: src/app/orders/page.tsx | P28: 2026-05-31 | Q28: 2026-09-12 | AF28: Indikator status pesanan di daftar kurang jelas | AG28: — | AH28: Badge status diperbarui (9e46c12) | AI28: 2026-09-12
A29: 3.e | B29: Marketplace (Produk) | C29: Halaman | D29: Detail & pelacakan pesanan | E29: Sedang Berjalan | F29: Halaman berjalan; pelacakan kurir belum tersambung (diverifikasi 30 Sep). | G29: https://saloka.id/orders/[order-id] | H29: Pembeli pesanan tersebut | I29: Stepper status (dibayar → disiapkan → dikirim → diterima), riwayat pelacakan, konfirmasi pesanan diterima, tulis ulasan. | J29: Pesanan, tahapan pelacakan, ulasan | K29: Order, OrderTracking, ProductReview, Wallet | L29: orders.getOrderDetail; reviews.createReview | M29: src/app/orders/[id]/page.tsx | N29: Minggu C: sinkronisasi status kurir | O29: Pelacakan diperbarui manual oleh merchant (input resi + ubah status). trackBiteshipWaybill ada tapi tidak dipanggil; belum ada webhook Biteship. Notifikasi WA status pesanan memakai nomor penerima hardcoded (orders.ts:138). | P29: 2026-05-31 | Q29: 2026-09-12
A30: 3.f | B30: Marketplace (Produk) | C30: Halaman | D30: Invoice pesanan | E30: Selesai | F30: Stabil sejak 29 Agu untuk cakupan saat ini; field pajak adalah jalur terpisah. | G30: https://saloka.id/orders/[order-id]/invoice | H30: Pembeli / merchant pesanan tersebut | I30: Invoice yang bisa dicetak. | J30: Pesanan, pembeli, merchant, total | K30: Order, User | L30: orders.getOrderInvoiceData | M30: src/app/orders/[id]/invoice/page.tsx | N30: Jalur paralel: Pajak (PPN / e-Faktur) — belum dimulai | O30: Belum ada field PPN / e-Faktur. | P30: 2026-05-31 | Q30: 2026-08-29
A31: 3.g | B31: Marketplace (Produk) | C31: Halaman Admin | D31: Admin · Katalog Produk | E31: Quality Check | F31: CMS direstrukturisasi 5 Sep. | G31: https://saloka.id/cms_admin/products | H31: Admin dengan izin “products” | I31: Moderasi katalog produk. | J31: Semua produk | K31: Product | L31: src/app/cms_admin/components/ProductsTab.tsx | M31: src/app/cms_admin/components/ProductsTab.tsx | P31: 2026-09-05 | Q31: 2026-09-05
A32: 4 | B32: Jasa | C32: Fitur | D32: Jasa | E32: Sedang Berjalan | F32: Daftar dan booking berjalan, tetapi ulasan tidak disimpan ke database dan production bisa menampilkan jasa contoh.
A33: 4.a | B33: Jasa | C33: Halaman | D33: Daftar jasa | E33: Sedang Berjalan | F33: Jalur data asli ada, tetapi production bisa fallback ke jasa contoh. | G33: https://saloka.id/jasa | H33: Semua orang | I33: Katalog jasa dengan pencarian dan filter. | J33: Jasa & penyedia | K33: Service, User | L33: services.getServicesAction | M33: src/app/jasa/JasaClient.tsx; src/app/jasa/page.tsx | O33: Fallback ke jasa contoh (mock-seed) jika database tidak mengembalikan data. | P33: 2026-08-15 | Q33: 2026-09-05 | AB33: Daftar jasa kosong di production | AC33: — | AD33: Fallback ke jasa contoh (a06f595) | AE33: 2026-09-05
A34: 4.b | B34: Jasa | C34: Halaman | D34: Detail & booking jasa | E34: Sedang Berjalan | F34: Booking berjalan; ulasan jasa hanya tersimpan di memori server. | G34: https://saloka.id/jasa/[service-id] | H34: Semua orang (booking perlu login) | I34: Detail dan booking jasa: kalender bulanan, satu tanggal atau rentang tanggal, durasi, biaya platform sesuai durasi, ulasan. | J34: Jasa, ketersediaan, booking, ulasan | K34: Service, ServiceAvailability, ServiceBooking, AuditLog | L34: services.getServiceByIdAction, getServiceAvailabilityAction, createServiceBookingAction, getServiceReviewsAction, submitServiceReviewAction | M34: src/app/jasa/[id]/ServiceBookingClient.tsx; src/app/jasa/[id]/page.tsx | O34: Ulasan jasa tidak punya tabel database (disimpan di memori server, hilang saat restart). | P34: 2026-08-15 | Q34: 2026-09-05 | AB34: Biaya platform tidak menyesuaikan durasi booking; booking rentang tanggal tidak tersedia untuk beberapa tipe jasa | AC34: — | AD34: Biaya sesuai durasi; rentang tanggal untuk semua tipe (0b50861, 9eb0129) | AE34: 2026-09-05
A35: 4.c | B35: Jasa | C35: Halaman Admin | D35: Admin · Jasa & Layanan | E35: Quality Check | F35: 2 dari 3 tab sudah dibuat. | G35: https://saloka.id/cms_admin/services/katalog | H35: Admin dengan izin “services” | I35: Katalog jasa, booking, dan jadwal. | J35: Jasa, booking | K35: Service, ServiceBooking | M35: src/app/cms_admin/components/ServicesTab.tsx | P35: 2026-09-05 | Q35: 2026-09-05
A36: 4.c.i | B36: Jasa | C36: Tab Admin | D36: Katalog Jasa | E36: Quality Check | F36: Sudah dibuat; CMS direstrukturisasi 5 Sep. | G36: https://saloka.id/cms_admin/services/katalog
A37: 4.c.ii | B37: Jasa | C37: Tab Admin | D37: Booking | E37: Quality Check | F37: Sudah dibuat; CMS direstrukturisasi 5 Sep. | G37: https://saloka.id/cms_admin/services/booking
A38: 4.c.iii | B38: Jasa | C38: Tab Admin | D38: Jadwal | E38: Belum Dimulai | F38: Menampilkan layar “belum tersedia”. | G38: https://saloka.id/cms_admin/services/jadwal | O38: Belum ada kalender ketersediaan lintas jasa untuk admin.
A39: 5 | B39: Snackbox | C39: Fitur | D39: Snackbox | E39: Sedang Berjalan | F39: Halaman pelanggan & checkout (digabung ke pesanan Marketplace) berjalan; 3 layar admin masih mock; v1 belum dinyatakan rilis (diverifikasi 30 Sep).
A40: 5.a | B40: Snackbox | C40: Halaman | D40: Halaman Snackbox | E40: Quality Check | F40: Perombakan besar 9 Sep; QA v1 / bug bash belum terdokumentasi. | G40: https://saloka.id/snackbox | H40: Semua orang | I40: Pemesanan snack box lokal: deteksi kelurahan lewat GPS/IP (deteksi ulang saat pengguna berpindah), pencarian kelurahan, tab kategori, produk dari merchant di area tersebut, sticky cart bar, CTA pendaftaran merchant. | J40: Lokasi terdeteksi (browser), kelurahan, produk Snackbox | K40: Product, User | L40: products.getSnackboxProducts; /api/geolocation/detect, /api/geolocation/reverse (ip-api + OpenStreetMap); /api/kelurahan/search (kodepos.vercel.app) | M40: src/app/snackbox/page.tsx; src/context/SnackboxContext.tsx; src/components/snackbox/ | N40: Minggu A (1–6 Sep): Snackbox v1 | O40: Rilis v1 belum dinyatakan; belum ada bug bash terdokumentasi; slider bagi hasil 15–20% dan pencarian kategori merchant belum di-QA; daftar kelurahan fallback ke data mock jika API kode pos gagal. | P40: 2026-08-29 | Q40: 2026-09-09 | AB40: Lokasi GPS kurang presisi dibanding onboarding; masalah tata letak mobile | AC40: — | AD40: Reverse-geocoding sama dengan onboarding; tata letak mobile diperbaiki (8133e77) | AE40: 2026-09-05
A41: 5.b | B41: Snackbox | C41: Alur | D41: Checkout Snackbox (keranjang bersama) | E41: Sedang Berjalan | F41: Memakai keranjang Marketplace yang masih dikerjakan. | G41: https://saloka.id/cart | H41: Pembeli yang sudah login | I41: Box Snackbox melewati keranjang & checkout bersama Marketplace. | M41: src/app/cart/page.tsx | N41: Minggu A / Minggu C | P41: 2026-05-30 | Q41: 2026-09-12
A42: 5.c | B42: Snackbox | C42: Halaman Admin | D42: Admin · Mitra & Produk Snackbox | E42: Quality Check | F42: Memakai tabel merchant & produk yang asli. | G42: https://saloka.id/cms_admin/snackbox-kurasi/merchant | H42: Admin dengan izin “snackbox-kurasi” | I42: Menyetujui merchant dan produk untuk Snackbox. | J42: Merchant, produk | K42: User, Product | M42: src/app/cms_admin/components/MerchantVerificationTab.tsx; src/app/cms_admin/components/ProductsTab.tsx | P42: 2026-09-05 | Q42: 2026-09-05
A43: 5.c.i | B43: Snackbox | C43: Tab Admin | D43: Mitra Snackbox | E43: Quality Check | F43: Data asli. | G43: https://saloka.id/cms_admin/snackbox-kurasi/merchant
A44: 5.c.ii | B44: Snackbox | C44: Tab Admin | D44: Produk Snackbox | E44: Quality Check | F44: Data asli (tabel yang sama dengan Katalog Produk). | G44: https://saloka.id/cms_admin/snackbox-kurasi/katalog
A45: 5.d | B45: Snackbox | C45: Halaman Admin | D45: Admin · Order History Snackbox | E45: Sedang Berjalan | F45: Masih ditandai mock di CMS (nav.config mock:true): tidak tersimpan ke database (diverifikasi 30 Sep). | G45: https://saloka.id/cms_admin/snackbox-order/pending | H45: Admin | I45: Meneruskan pesanan Snackbox ke mitra kue lokal (tab: Pending, Dihubungi, Konfirmasi, Ditolak). | J45: Hanya pesanan contoh | M45: src/app/cms_admin/nav.config.ts | N45: Minggu A | O45: Belum terhubung ke pesanan asli. | P45: 2026-09-05 | Q45: 2026-09-13
A46: 5.e | B46: Snackbox | C46: Halaman Admin | D46: Admin · Coverage Kelurahan | E46: Sedang Berjalan | F46: Masih mock; daftar coverage hanya tersimpan di localStorage browser (diverifikasi 30 Sep). | G46: https://saloka.id/cms_admin/snackbox-coverage | H46: Admin | I46: Kelurahan yang dilayani Snackbox; pencarian kelurahan nasional dengan aktivasi sekali klik. | J46: Daftar coverage (localStorage browser) | L46: /api/kelurahan/search | M46: src/app/cms_admin/components/KelurahanTab.tsx | N46: Minggu A | O46: Coverage tidak disimpan di database, sehingga tidak dibagikan antar admin atau perangkat. | P46: 2026-09-05 | Q46: 2026-09-05
A47: 5.f | B47: Snackbox | C47: Halaman Admin | D47: Admin · Payout Mitra | E47: Belum Dimulai | F47: Masih mock: MOCK_BATCHES hardcoded dan tombol payout tidak memindahkan uang (diverifikasi 30 Sep). | G47: https://saloka.id/cms_admin/snackbox-payout | H47: Admin | I47: Pencairan dana terjadwal ke mitra Snackbox. | J47: Batch contoh yang di-hardcode | M47: src/app/cms_admin/components/SnackboxPayoutTab.tsx | O47: Logika payout asli belum dibuat. | P47: 2026-09-05 | Q47: 2026-09-05
A48: 6 | B48: Komunitas | C48: Fitur | D48: Komunitas | E48: Quality Check | F48: Sebagian besar modul memakai data asli; QA mobile & feature freeze Minggu B belum disetujui; tab Event belum tersimpan ke database; 10 modul template Perkumpulan masih placeholder.
A49: 6.a | B49: Komunitas | C49: Halaman | D49: Community Hub (direktori) | E49: Quality Check | F49: Diubah 13 Sep; QA mobile & freeze belum selesai. | G49: https://saloka.id/community | H49: Semua orang; membuat/bergabung perlu login (plus KYC jika admin mengaktifkannya) | I49: Direktori semua Perkumpulan & Koperasi dengan badge tipe/tier dan harga bergabung; widget “Komunitas & Role Saya” dengan pengalih komunitas utama; form buat komunitas — Perkumpulan (template Society / Business / Education / Culinary; Reguler gratis) atau Koperasi (Reguler / Premium / Max, aktivasi berbayar). | J49: Komunitas, badge & harga, keanggotaan dan peran pengguna, pengaturan KYC global | K49: Community, CommunityMembership, User, SystemSetting | L49: community.getIndukCommunities, createIndukCommunity, joinIndukCommunity, getUserCommunitiesWithRolesAction, switchActiveIndukCommunityAction; admin.getGlobalKycSettingAction; /api/upload | M49: src/app/community/CommunityDirectoryClient.tsx; src/app/community/CreateCommunityModal.tsx; src/lib/community-badge.ts; src/lib/community-templates.ts | N49: Minggu B (7–13 Sep): Finalisasi Sistem Komunitas | O49: QA mobile dan feature freeze belum disetujui. | P49: 2026-08-30 | Q49: 2026-09-13 | T49: 1. Pendaftaran Perkumpulan meminta pembayaran 2. Bergabung ke komunitas lain menimpa keanggotaan / status pending sebelumnya 3. Perkumpulan menerima bonus koin milik Koperasi | U49: 1. — 2. — 3. — | V49: 1. Perkumpulan gratis; hanya Koperasi yang membayar aktivasi (7833a69) 2. Status per komunitas, banyak keanggotaan tetap tersimpan (c4bbe99) 3. Bonus koin dibatasi untuk tier Koperasi (44ab8e8) | W49: 1. 2026-08-05 2. 2026-08-08 3. 2026-08-08 | X49: Carousel kartu peran tidak bisa di-scroll di mobile; avatar bukan foto asli | Y49: — | Z49: Scroll sentuh, avatar asli, modal “Lihat semua” (b61c101, a78d38c, 182c386) | AA49: 2026-08-30 | AB49: Biaya bergabung menampilkan nilai dummy; badge berbayar hilang di tier Koperasi & Perkumpulan Premium | AC49: — | AD49: Biaya bergabung asli; badge ditegakkan (c345a34, 14b1281) | AE49: 2026-09-06 | AF49: Beberapa komunitas Koperasi & Perkumpulan Premium tampil sebagai gratis | AG49: — | AH49: Selalu tampil sebagai berbayar (f2c1a05) | AI49: 2026-09-07
A50: 6.b | B50: Komunitas | C50: Halaman | D50: Landing page komunitas (publik) | E50: Quality Check | F50: Diubah 13 Sep; perbaikan jumlah anggota belum di-commit. | G50: https://saloka.id/community/[community-id] | H50: Semua orang — semua tipe & tier | I50: Halaman publik satu komunitas: hero & badge, tentang & legalitas (akta, AHU, NPWP), produk resmi dan produk anggota, tombol bergabung. Gratis untuk Perkumpulan Reguler; biaya bergabung berbayar (DOKU) untuk Perkumpulan Premium dan semua tier Koperasi (Reguler / Premium / Max). | J50: Profil & desain landing komunitas, biaya bergabung, jumlah anggota, siapa yang mereferensikan anggota baru | K50: Community, CommunityMembership, CommunityReferralLog, Wallet, WalletTransaction | L50: community.joinIndukCommunity, payCommunityJoinFeeAction; /api/payment/checkout & /api/payment/verify (JOIN_FEE) | M50: src/app/community/[id]/LandingPageView.tsx; src/app/community/[id]/page.tsx | N50: Minggu B | O50: Membuka id komunitas yang tidak dikenal diam-diam membuat komunitas baru (catatan Phase 6); id yang mengandung “dummy”/“perahu” menampilkan data contoh. | P50: 2026-08-12 | Q50: 2026-09-13 | T50: Error “Komunitas tidak ditemukan” pada komunitas yang valid | U50: — | V50: Sinkronisasi skema + fallback seeding (49f8e69) | W50: 2026-07-15 | AB50: Bergabung / membayar biaya bergabung gagal (user undefined, update database bermasalah) | AC50: — | AD50: Proses bergabung & update pembayaran diperbaiki (14236eb, 44b89e8) | AE50: 2026-09-06 | AF50: 1. Beberapa komunitas berbayar tampil sebagai gratis 2. Jumlah anggota ikut menghitung anggota yang dikeluarkan; daftar anggota usang tepat setelah membayar biaya bergabung | AG50: 1. — 2. — | AH50: 1. Selalu tampil sebagai berbayar (f2c1a05) 2. Anggota yang dikeluarkan difilter; cache anggota/statistik dibersihkan | AI50: 1. 2026-09-07 2. Sedang dikerjakan (belum di-commit)
A51: 6.c | B51: Komunitas | C51: Halaman | D51: Dashboard komunitas (area anggota) | E51: Quality Check | F51: Diubah 13 Sep; QA mobile belum selesai. | G51: https://saloka.id/community/[community-id]?view=dashboard&tab=beranda | H51: Anggota. Menu tergantung tipe: Koperasi (semua tier) atau template Perkumpulan; pengurus mendapat tab tambahan. | I51: Ruang kerja dengan sidebar untuk satu komunitas. Tab di bawah. | K51: Community, CommunityMembership | M51: src/app/community/[id]/CommunityDetailClient.tsx | N51: Minggu B | P51: 2026-06-18 | Q51: 2026-09-13 | T51: 1. Tombol top-up dummy memungkinkan pembayaran tanpa uang asli 2. Halaman komunitas lambat dimuat | U51: 1. — 2. — | V51: 1. Dihapus; pembayaran QRIS/bank asli diwajibkan (f82cc30) 2. Data dimuat secara paralel (5d6e3fc) | W51: 1. 2026-07-23 2. 2026-07-23 | X51: Diskusi/Event/Galeri/Produk/Ketua/Legalitas menampilkan data yang sama untuk setiap komunitas | Y51: — | Z51: Data diambil per komunitas (6fa23e9) | AA51: 2026-08-23
A52: 6.c.i | B52: Komunitas | C52: Tab | D52: Beranda | E52: Quality Check | F52: Statistik asli sejak 12 Agu; beberapa kotak angka tetap 0. | G52: https://saloka.id/community/[community-id]?view=dashboard&tab=beranda | H52: Semua tipe & template | I52: Kotak statistik + feed aktivitas dengan filter. Koperasi: anggota, total simpanan, SHU tahun ini, unit usaha. Kotak statistik Perkumpulan tergantung template. | J52: Jumlah anggota, total simpanan, SHU, merchant, event, diskusi | K52: Community, CommunityMembership, CooperativeSavingsTransaction, ShuConfig | L52: community.getCommunityRealStatsAction; savings.getCommunitySavingsSummaryAction | M52: src/app/community/[id]/CommunityDetailClient.tsx | N52: Minggu B | O52: Kotak statistik untuk modul yang belum dibuat di-hardcode 0 (Pelatihan, Kelas, Kompetisi, Supplier). | P52: 2026-06-18 | Q52: 2026-09-13
A53: 6.c.ii | B53: Komunitas | C53: Tab | D53: Diskusi | E53: Quality Check | F53: Penyimpanan diperbaiki 5 Sep. | G53: https://saloka.id/community/[community-id]?view=dashboard&tab=diskusi | H53: Semua tipe & template | I53: Forum: thread, balasan, suka, pin/tutup, jawaban membantu & jawaban terbaik. | J53: Thread & balasan | K53: SystemSetting (satu nilai JSON per komunitas; tabel Discussion/DiscussionReply ada tetapi tidak dipakai) | L53: discussion.* (11 action) | M53: src/components/community/DiscussionForum.tsx; src/app/actions/discussion.ts | N53: Minggu B | O53: Seluruh forum disimpan sebagai satu nilai JSON per komunitas, sehingga dua postingan di saat bersamaan bisa saling menimpa. | P53: 2026-08-27 | Q53: 2026-09-05 | X53: Diskusi tidak terlihat oleh pengguna lain; suka & komentar tidak berfungsi; hilang saat refresh | Y53: — | Z53: Terlihat lintas pengguna, suka/komentar aktif, data & tab tetap saat refresh (2125df1, 93a0273) | AA53: 2026-08-29 | AB53: Diskusi/balasan baru sempat hilang sesaat | AC53: — | AD53: Langsung disimpan ke database (0a8a59d) | AE53: 2026-09-05
A54: 6.c.iii | B54: Komunitas | C54: Tab | D54: Pengumuman | E54: Quality Check | F54: Data asli; bagian dari QA Minggu B. | G54: https://saloka.id/community/[community-id]?view=dashboard&tab=pengumuman | H54: Semua tipe & template | I54: Pengumuman: buat, pin, publikasikan. | J54: Pengumuman | K54: Announcement | L54: announcements.* | M54: src/app/actions/announcements.ts | N54: Minggu B | P54: 2026-08-14 | Q54: 2026-09-13
A55: 6.c.iv | B55: Komunitas | C55: Tab | D55: Anggota | E55: Quality Check | F55: Perbaikan jumlah anggota belum di-commit. | G55: https://saloka.id/community/[community-id]?view=dashboard&tab=anggota | H55: Koperasi (semua tier); Perkumpulan Society, Business, Culinary (tidak ada di menu Education) | I55: Daftar anggota; ketua/admin bisa mengeluarkan anggota. | J55: Anggota & peran | K55: CommunityMembership (removedAt), User | L55: community.getIndukCommunityMembersAction, kickCommunityMemberAction | M55: src/app/community/[id]/CommunityDetailClient.tsx | N55: Minggu B | P55: 2026-06-18 | Q55: 2026-09-13 | X55: Anggota yang dikeluarkan masih muncul di daftar setelah refresh | Y55: — | Z55: Data keanggotaan dihapus; daftar diperbarui (122a20d, 2d5bbed, 06e7ea5) | AA55: 2026-08-23 | AF55: Jumlah anggota ikut menghitung anggota yang dikeluarkan | AG55: — | AH55: Anggota yang dikeluarkan difilter; cache dibersihkan | AI55: Sedang dikerjakan (belum di-commit)
A56: 6.c.v | B56: Komunitas | C56: Tab | D56: Produk Komunitas | E56: Quality Check | F56: Penyimpanan diperbaiki 5 Sep. | G56: https://saloka.id/community/[community-id]?view=dashboard&tab=produk_komunitas | H56: Semua tipe & template | I56: Produk resmi komunitas; Koperasi juga menampilkan produk koperasi. | J56: Produk resmi | K56: SystemSetting (JSON per komunitas); CooperativeProduct (Koperasi) | L56: community-products.*; community.create/update/deleteCooperativeProductAction | M56: src/app/actions/community-products.ts | N56: Minggu B | O56: Produk resmi disimpan sebagai satu nilai JSON per komunitas (risiko saling menimpa yang sama dengan Diskusi). | P56: 2026-08-29 | Q56: 2026-09-13 | AB56: Produk resmi komunitas tidak tersimpan; modal tambah tidak ada | AC56: — | AD56: Modal + penyimpanan ke database (e14ef4d) | AE56: 2026-09-05
A57: 6.c.vi | B57: Komunitas | C57: Tab | D57: Produk Anggota / Marketplace | E57: Quality Check | F57: Modal tambah/edit diperbaiki 5 Sep. | G57: https://saloka.id/community/[community-id]?view=dashboard&tab=marketplace | H57: Koperasi (“Marketplace”); Perkumpulan Business (“Produk UMKM”), Culinary (“Produk”), Society (“Produk Anggota”) | I57: Produk milik anggota yang ditampilkan di dalam komunitas. | J57: Produk anggota | K57: Product | L57: products.createMemberProductAction, updateMemberProductAction, deleteMemberProductAction | M57: src/app/actions/products.ts | N57: Minggu B | P57: 2026-05-30 | Q57: 2026-09-12 | AB57: Katalog produk anggota tidak punya modal tambah/edit | AC57: — | AD57: Modal dan handler ditambahkan (335f56e, e14ef4d) | AE57: 2026-09-05
A58: 6.c.vii | B58: Komunitas | C58: Tab | D58: Event | E58: Sedang Berjalan | F58: Tidak ada tabel database: event disimpan di memori server. | G58: https://saloka.id/community/[community-id]?view=dashboard&tab=event | H58: Perkumpulan Society, Business, Education, Culinary (tidak ada di menu Koperasi) | I58: Daftar event, buat/edit, pendaftaran. | J58: Event & pendaftar | K58: Tidak ada (tidak ada tabel CommunityEvent) | L58: community-events.* | M58: src/app/actions/community-events.ts | N58: Minggu B | O58: Setiap komunitas dimulai dengan 3 event contoh yang sama; event baru bisa hilang setelah redeploy/restart. | P58: 2026-08-29 | Q58: 2026-09-13 | X58: Tombol edit event tidak berfungsi | Y58: — | Z58: Modal edit ditambahkan (e88cd8f) | AA58: 2026-08-30
A59: 6.c.viii | B59: Komunitas | C59: Tab | D59: Galeri | E59: Quality Check | F59: Penyimpanan diperbaiki 5 Sep. | G59: https://saloka.id/community/[community-id]?view=dashboard&tab=galeri | H59: Perkumpulan Society, Culinary | I59: Galeri foto dengan lightbox; tambah/hapus. | J59: Item galeri | K59: SystemSetting (JSON per komunitas) | L59: community-gallery.* | M59: src/app/actions/community-gallery.ts | N59: Minggu B | O59: Disimpan sebagai satu nilai JSON per komunitas (risiko saling menimpa yang sama dengan Diskusi). | P59: 2026-08-29 | Q59: 2026-09-09 | X59: Tombol edit galeri tidak berfungsi | Y59: — | Z59: Modal edit ditambahkan (e88cd8f) | AA59: 2026-08-30 | AB59: Galeri ter-reset setelah refresh; tombol lightbox tidak merespons | AC59: — | AD59: Disimpan ke database; tombol diperbaiki (a7afe8b, 1370479) | AE59: 2026-09-05
A60: 6.c.ix | B60: Komunitas | C60: Tab | D60: Aktivitas | E60: Quality Check | F60: Dibentuk dari data modul lain. | G60: https://saloka.id/community/[community-id]?view=dashboard&tab=aktivitas | H60: Perkumpulan Society | I60: Linimasa kejadian di komunitas. | J60: Diambil dari diskusi, event, produk, dll. | M60: src/app/community/[id]/CommunityDetailClient.tsx | N60: Minggu B | P60: 2026-06-18 | Q60: 2026-09-13
A61: 6.c.x | B61: Komunitas | C61: Tab | D61: Tentang | E61: Quality Check | F61: Data asli; bagian dari QA Minggu B. | G61: https://saloka.id/community/[community-id]?view=dashboard&tab=tentang | H61: Semua tipe & template | I61: Tentang komunitas, kepengurusan (ketua), dan dokumen legal. | J61: Profil & field legal komunitas | K61: Community | M61: src/app/community/[id]/CommunityDetailClient.tsx | N61: Minggu B | P61: 2026-06-18 | Q61: 2026-09-13
A62: 6.c.xi | B62: Komunitas | C62: Tab | D62: Simpanan | E62: Quality Check | F62: Pembayaran DOKU ditambahkan 12 Sep. | G62: https://saloka.id/community/[community-id]?view=dashboard&tab=simpanan | H62: Hanya Koperasi (sukarela: Premium & Max) | I62: Simpanan anggota: simpanan pokok & wajib (semua tier Koperasi), simpanan sukarela (Premium & Max); bayar dengan wallet atau DOKU; riwayat. | J62: Transaksi & total simpanan | K62: CooperativeSavingsTransaction (orderId unique), CommunityMembership, Wallet, WalletTransaction | L62: savings.recordSavingsTransactionAction, paySavingsViaWalletAction, getCommunitySavingsSummaryAction; /api/payment/checkout (SAVINGS) | M62: src/app/actions/savings.ts | N62: Minggu B | P62: 2026-08-12 | Q62: 2026-09-13 | T62: Anggota tidak bisa mencatat setoran sendiri; kartu & riwayat simpanan tidak dari database | U62: — | V62: Setoran mandiri diaktifkan; ringkasan & riwayat dari database (06f7d80, 7daa37e, c9728e3) | W62: 2026-08-12
A63: 6.c.xii | B63: Komunitas | C63: Tab | D63: SHU | E63: Quality Check | F63: Perbaikan rumus 12–15 Agu; transfer ke wallet belum dibuat. | G63: https://saloka.id/community/[community-id]?view=dashboard&tab=shu | H63: Hanya Koperasi (semua tier) | I63: Sisa hasil usaha: atur % Jasa Modal / Jasa Usaha, hitung & simpan distribusi per anggota; anggota melihat estimasinya. | J63: Konfigurasi SHU & distribusi anggota | K63: ShuConfig, ShuMemberDistribution, CommunityMembership | L63: shu.calculateAndSaveShuAction, getCommunityShuDataAction, getUserShuSummaryAction | M63: src/lib/shu-calculator.ts | N63: Minggu B | O63: SHU dihitung tetapi tidak ditransfer ke wallet anggota (Phase 6). | P63: 2026-07-22 | Q63: 2026-09-13 | T63: 1. SHU tampil 0 untuk anggota dan rumus distribusi salah 2. Anggota tidak melihat SHU sebelum distribusi final; pemetaan merchant untuk pesanan selesai salah | U63: 1. — 2. — | V63: 1. Anggota terbaca benar; rumus proporsional; validasi total 100% (2dd43ca, d4c6e1c, 74562fd) 2. Estimasi SHU ditampilkan; pemetaan diperbaiki (0451f94, 0a1eb15) | W63: 1. 2026-08-12 2. 2026-08-15
A64: 6.c.xiii | B64: Komunitas | C64: Tab | D64: Laporan | E64: Quality Check | F64: Data asli; bagian dari QA Minggu B. | G64: https://saloka.id/community/[community-id]?view=dashboard&tab=laporan | H64: Hanya Koperasi | I64: Laporan koperasi: buat, edit, publikasikan. | J64: Laporan | K64: CooperativeReport | L64: reports.* | M64: src/app/actions/reports.ts | N64: Minggu B | P64: 2026-08-14 | Q64: 2026-09-13
A65: 6.c.xiv | B65: Komunitas | C65: Tab | D65: Pendanaan | E65: Sedang Berjalan | F65: Pinjaman bisa disetujui tetapi tidak pernah dicairkan. | G65: https://saloka.id/community/[community-id]?view=dashboard&tab=pendanaan | H65: Hanya Koperasi Max (PRO); tier lain melihat “Fitur Pendanaan Belum Aktif” | I65: Proyek pendanaan merchant dan pengajuan pinjaman anggota. | J65: Proyek pendanaan, pengajuan pinjaman | K65: MerchantFundingProject, CooperativeLoan | L65: community.get/create/deleteMerchantFundingProjectAction, submit/approve/rejectCooperativeLoanAction | M65: src/app/community/[id]/CommunityDetailClient.tsx | N65: Minggu B | O65: Pencairan pinjaman belum dibuat (Phase 6); batasan tier tidak ditegakkan di server. | P65: 2026-06-18 | Q65: 2026-09-13
A66: 6.c.xv | B66: Komunitas | C66: Tab | D66: Business Matching | E66: Belum Dimulai | F66: Tab hanya menampilkan placeholder "Segera Hadir" (ComingSoonTab); belum ada backend. Diverifikasi ulang 30 Sep. | G66: https://saloka.id/community/[community-id]?view=dashboard&tab=business_matching | H66: Perkumpulan Business | I66: Hanya placeholder. | M66: src/app/community/[id]/CommunityDetailClient.tsx | N66: Minggu B | O66: Modul belum dibangun — bangun, atau sembunyikan lewat Feature Control sampai siap. | P66: 2026-06-18 | Q66: 2026-09-13
A67: 6.c.xvi | B67: Komunitas | C67: Tab | D67: Pelatihan | E67: Belum Dimulai | F67: Tab hanya menampilkan placeholder "Segera Hadir" (ComingSoonTab); belum ada backend. Diverifikasi ulang 30 Sep. | G67: https://saloka.id/community/[community-id]?view=dashboard&tab=pelatihan | H67: Perkumpulan Business | I67: Hanya placeholder. | M67: src/app/community/[id]/CommunityDetailClient.tsx | N67: Minggu B | O67: Modul belum dibangun — bangun, atau sembunyikan lewat Feature Control sampai siap. | P67: 2026-06-18 | Q67: 2026-09-13
A68: 6.c.xvii | B68: Komunitas | C68: Tab | D68: Mentor | E68: Belum Dimulai | F68: Tab hanya menampilkan placeholder "Segera Hadir" (ComingSoonTab); belum ada backend. Diverifikasi ulang 30 Sep. | G68: https://saloka.id/community/[community-id]?view=dashboard&tab=mentor | H68: Perkumpulan Business, Education | I68: Hanya placeholder. | M68: src/app/community/[id]/CommunityDetailClient.tsx | N68: Minggu B | O68: Modul belum dibangun — bangun, atau sembunyikan lewat Feature Control sampai siap. | P68: 2026-06-18 | Q68: 2026-09-13
A69: 6.c.xviii | B69: Komunitas | C69: Tab | D69: Kolaborasi | E69: Belum Dimulai | F69: Tab hanya menampilkan placeholder "Segera Hadir" (ComingSoonTab); belum ada backend. Diverifikasi ulang 30 Sep. | G69: https://saloka.id/community/[community-id]?view=dashboard&tab=kolaborasi | H69: Perkumpulan Business | I69: Hanya placeholder. | M69: src/app/community/[id]/CommunityDetailClient.tsx | N69: Minggu B | O69: Modul belum dibangun — bangun, atau sembunyikan lewat Feature Control sampai siap. | P69: 2026-06-18 | Q69: 2026-09-13
A70: 6.c.xix | B70: Komunitas | C70: Tab | D70: Kelas | E70: Belum Dimulai | F70: Tab hanya menampilkan placeholder "Segera Hadir" (ComingSoonTab); belum ada backend. Diverifikasi ulang 30 Sep. | G70: https://saloka.id/community/[community-id]?view=dashboard&tab=kelas | H70: Perkumpulan Education | I70: Hanya placeholder. | M70: src/app/community/[id]/CommunityDetailClient.tsx | N70: Minggu B | O70: Modul belum dibangun — bangun, atau sembunyikan lewat Feature Control sampai siap. | P70: 2026-06-18 | Q70: 2026-09-13
A71: 6.c.xx | B71: Komunitas | C71: Tab | D71: Kompetisi | E71: Belum Dimulai | F71: Tab hanya menampilkan placeholder "Segera Hadir" (ComingSoonTab); belum ada backend. Diverifikasi ulang 30 Sep. | G71: https://saloka.id/community/[community-id]?view=dashboard&tab=kompetisi | H71: Perkumpulan Education | I71: Hanya placeholder. | M71: src/app/community/[id]/CommunityDetailClient.tsx | N71: Minggu B | O71: Modul belum dibangun — bangun, atau sembunyikan lewat Feature Control sampai siap. | P71: 2026-06-18 | Q71: 2026-09-13
A72: 6.c.xxi | B72: Komunitas | C72: Tab | D72: Startup | E72: Belum Dimulai | F72: Tab hanya menampilkan placeholder "Segera Hadir" (ComingSoonTab); belum ada backend. Diverifikasi ulang 30 Sep. | G72: https://saloka.id/community/[community-id]?view=dashboard&tab=startup | H72: Perkumpulan Education | I72: Hanya placeholder. | M72: src/app/community/[id]/CommunityDetailClient.tsx | N72: Minggu B | O72: Modul belum dibangun — bangun, atau sembunyikan lewat Feature Control sampai siap. | P72: 2026-06-18 | Q72: 2026-09-13
A73: 6.c.xxii | B73: Komunitas | C73: Tab | D73: Merchant | E73: Belum Dimulai | F73: Tab hanya menampilkan placeholder "Segera Hadir" (ComingSoonTab); belum ada backend. Diverifikasi ulang 30 Sep. | G73: https://saloka.id/community/[community-id]?view=dashboard&tab=merchant | H73: Perkumpulan Culinary | I73: Hanya placeholder. | M73: src/app/community/[id]/CommunityDetailClient.tsx | N73: Minggu B | O73: Modul belum dibangun — bangun, atau sembunyikan lewat Feature Control sampai siap. | P73: 2026-06-18 | Q73: 2026-09-13
A74: 6.c.xxiii | B74: Komunitas | C74: Tab | D74: Supplier | E74: Belum Dimulai | F74: Tab hanya menampilkan placeholder "Segera Hadir" (ComingSoonTab); belum ada backend. Diverifikasi ulang 30 Sep. | G74: https://saloka.id/community/[community-id]?view=dashboard&tab=supplier | H74: Perkumpulan Culinary | I74: Hanya placeholder. | M74: src/app/community/[id]/CommunityDetailClient.tsx | N74: Minggu B | O74: Modul belum dibangun — bangun, atau sembunyikan lewat Feature Control sampai siap. | P74: 2026-06-18 | Q74: 2026-09-13
A75: 6.c.xxiv | B75: Komunitas | C75: Tab | D75: Promo | E75: Belum Dimulai | F75: Tab hanya menampilkan placeholder "Segera Hadir" (ComingSoonTab); belum ada backend. Diverifikasi ulang 30 Sep. | G75: https://saloka.id/community/[community-id]?view=dashboard&tab=promo | H75: Perkumpulan Culinary | I75: Hanya placeholder. | M75: src/app/community/[id]/CommunityDetailClient.tsx | N75: Minggu B | O75: Modul belum dibangun — bangun, atau sembunyikan lewat Feature Control sampai siap. | P75: 2026-06-18 | Q75: 2026-09-13
A76: 6.c.xxv | B76: Komunitas | C76: Tab | D76: Desain Landing | E76: Quality Check | F76: Diubah 13 Sep. | G76: https://saloka.id/community/[community-id]?view=dashboard&tab=desain_landing | H76: Ketua, admin, super admin — semua tipe | I76: Editor landing page: hero, bagian-bagian halaman, toggle produk resmi vs produk anggota. | J76: Desain landing | K76: Community (landingPageConfig) | L76: community.updateIndukCommunity | M76: src/app/community/[id]/LandingPageEditor.tsx | N76: Minggu B | P76: 2026-08-12 | Q76: 2026-09-13
A77: 6.c.xxvi | B77: Komunitas | C77: Tab | D77: Afiliasi Saya | E77: Quality Check | F77: Perhitungan payout & perlindungan loop dibangun ulang 13 Sep; perlu diuji ulang. | G77: https://saloka.id/community/[community-id]?view=dashboard&tab=afiliasi_saya | H77: Anggota komunitas berbayar dengan program affiliate aktif (Perkumpulan Premium, Koperasi semua tier) | I77: Link referral pribadi dan komisi multi-tier dari biaya bergabung anggota baru. | J77: Referral, pembayaran komisi | K77: CommunityReferralLog, CommunityMembership (referrerId), Wallet, WalletTransaction | L77: community-referral.getMyCommunityAffiliateSummary, processMultiTierReferralPayout | M77: src/lib/referral-payout.ts | N77: Minggu B | P77: 2026-09-13 | Q77: 2026-09-13 | AF77: Komisi nominal dihitung sebagai persentase; sisa dana dikirim ke penerima fallback yang di-hardcode; loop referral bisa terjadi | AG77: — | AH77: Perhitungan payout dibangun ulang, pembagian biaya bergabung ditegakkan, pengecekan loop + script audit (2d53f00, 5a3dcb0) | AI77: 2026-09-13
A78: 6.c.xxvii | B78: Komunitas | C78: Tab | D78: Pengaturan | E78: Quality Check | F78: Perbaikan sinkronisasi pengaturan belum di-commit. | G78: https://saloka.id/community/[community-id]?view=dashboard&tab=pengaturan | H78: Ketua, admin — semua tipe | I78: Toggle modul & template (Perkumpulan), biaya bergabung & komisi referral (persentase atau nominal; biaya bergabung = anggaran referral + bagian komunitas), kunci rekrutmen, upgrade tier. | J78: Modul aktif, biaya bergabung, metode komisi, kunci rekrutmen, tier | K78: Community (disabledModules, joinFee, commissionMethod, isRecruitmentLocked) | L78: community.updateIndukCommunity, upgradeCommunityTierAction; community-referral.updateCommunityReferralConfig | M78: src/app/community/[id]/CommunityDetailClient.tsx | N78: Minggu B | O78: Upgrade tier gratis dan instan — belum ada penagihan (Phase 6). | P78: 2026-06-18 | Q78: 2026-09-13 | AF78: Pengaturan yang disimpan (menu, biaya bergabung, tier) masih menampilkan nilai lama di Hub dan CMS | AG78: — | AH78: Cache dibersihkan setiap kali menyimpan | AI78: Sedang dikerjakan (belum di-commit)
A79: 6.d | B79: Komunitas | C79: Halaman | D79: Koin komunitas (kas) | E79: Quality Check | F79: Diubah 13 Sep (top-up DOKU). | G79: https://saloka.id/community/[community-id]/coin | H79: Ketua atau admin — semua tipe (kelayakan pinjaman berlaku untuk Koperasi) | I79: Saldo koin komunitas, top-up via DOKU, riwayat koin, kelayakan akses pinjaman. | J79: Saldo & riwayat koin komunitas | K79: Community (coinBalance), CoinTransaction (orderId unique), CoinSupplyLog | L79: coin.getCommunityCoinBalance, checkCommunityLoanEligibility; /api/payment/checkout & /verify (COIN_TOPUP) | M79: src/app/community/[id]/coin/page.tsx | N79: Minggu B / C | O79: Koin komunitas, koin pengguna, wallet, dan “kas” adalah saldo berbeda tetapi namanya dipakai bergantian (Phase 6). | P79: 2026-06-25 | Q79: 2026-09-13
A80: 6.e | B80: Komunitas | C80: Halaman Admin | D80: Admin · Komunitas Induk | E80: Quality Check | F80: Diubah 13 Sep; perbaikan jumlah anggota belum di-commit. | G80: https://saloka.id/cms_admin/communities/daftar | H80: Admin dengan izin “communities” | I80: Kelola semua komunitas, invoice keanggotaan, moderasi forum, laporan, dan aturan KYC. | J80: Komunitas, anggota, invoice, postingan, laporan | K80: Community, CommunityMembership, Post, Comment, CooperativeReport, SystemSetting | M80: src/app/cms_admin/components/CommunityTab.tsx | N80: Minggu B | P80: 2026-09-05 | Q80: 2026-09-13
A81: 6.e.i | B81: Komunitas | C81: Tab Admin | D81: Daftar | E81: Quality Check | F81: Perbaikan jumlah anggota/data usang belum di-commit. | G81: https://saloka.id/cms_admin/communities/daftar | I81: Daftar, buat, edit, hapus komunitas; keluarkan anggota. | L81: admin.getCommunitiesAdminAction, create/update/deleteCommunityAdminAction, kickMemberFromCommunityAdminAction | X81: Jumlah/daftar anggota di admin tidak sinkron dengan keanggotaan asli | Y81: — | Z81: Jumlah dibaca dari data keanggotaan; konfirmasi kick (f393d1e, 6461060) | AA81: 2026-08-23 | AF81: CMS menghitung anggota yang dikeluarkan dan menampilkan data komunitas usang setelah edit/bergabung/pembayaran | AG81: — | AH81: Anggota yang dikeluarkan difilter; cache CMS diperbarui | AI81: Sedang dikerjakan (belum di-commit)
A82: 6.e.ii | B82: Komunitas | C82: Tab Admin | D82: Invoice Keanggotaan | E82: Quality Check | F82: Data asli. | G82: https://saloka.id/cms_admin/communities/invoice | I82: Verifikasi pembayaran keanggotaan. | L82: admin.getInvoiceMembershipsAction, verifyInvoiceMembershipAction
A83: 6.e.iii | B83: Komunitas | C83: Tab Admin | D83: Moderasi Forum | E83: Quality Check | F83: Data asli. | G83: https://saloka.id/cms_admin/communities/forum | I83: Hapus postingan dan komentar. | K83: Post, Comment | L83: community.deletePostAction, deleteCommentAction | O83: Memoderasi data Post/Comment; thread Diskusi komunitas disimpan terpisah — cek apakah muncul di sini.
A84: 6.e.iv | B84: Komunitas | C84: Tab Admin | D84: Laporan | E84: Quality Check | F84: Data asli. | G84: https://saloka.id/cms_admin/communities/laporan | I84: Semua laporan koperasi. | K84: CooperativeReport | M84: src/app/cms_admin/components/CooperativeReportsTab.tsx | P84: 2026-09-05 | Q84: 2026-09-05
A85: 6.e.v | B85: Komunitas | C85: Tab Admin | D85: Pengaturan KYC | E85: Selesai | F85: Disimpan di database sejak 1 Agu; tidak ada masalah sejak itu. | G85: https://saloka.id/cms_admin/communities/kyc | I85: Menyalakan/mematikan aturan “wajib KYC untuk membuat komunitas”. | K85: SystemSetting | L85: admin.getGlobalKycSettingAction, updateGlobalKycSettingAction | T85: Pengaturan KYC global ter-reset setiap server restart | U85: — | V85: Disimpan di database (2a1a5be) | W85: 2026-08-01
A86: 7 | B86: Pembayaran, Wallet & Koin | C86: Fitur | D86: Pembayaran, Wallet & Koin | E86: Sedang Berjalan | F86: DOKU & Biteship terintegrasi 12–13 Sep dengan perbaikan keamanan; verifikasi production, pembersihan vendor lama, dan sinkronisasi pengiriman masih tersisa (Minggu C).
A87: 7.a | B87: Pembayaran, Wallet & Koin | C87: Halaman | D87: Wallet | E87: Quality Check | F87: Deposit DOKU & perbaikan keamanan 12–13 Sep; perlu diuji ulang. | G87: https://saloka.id/wallet | H87: Pengguna yang sudah login | I87: Saldo dan riwayat, top-up dengan DOKU (tombol nominal cepat), tarik dana ke rekening bank. | J87: Saldo wallet, deposit, penarikan | K87: Wallet, WalletTransaction | L87: wallet-affiliate.getWalletDetails, withdrawFunds; /api/doku/direct, /api/doku/verify, /api/doku/notification | M87: src/app/wallet/page.tsx | N87: Minggu C | O87: Verifikasi akun production DOKU belum selesai; tombol bypass QRIS sandbox dibuat selalu terlihat 12 Sep — sembunyikan sebelum peluncuran. | P87: 2026-05-30 | Q87: 2026-09-12 | AF87: 1. Deposit dikreditkan sebelum DOKU mengonfirmasi pembayaran 2. Tidak ada batas minimum/maksimum deposit di sisi server | AG87: 1. — 2. — | AH87: 1. Cek status DOKU sebelum mengkreditkan (0b61de7) 2. Batas bawah dan atas ditegakkan (99a06a9) | AI87: 1. 2026-09-12 2. 2026-09-13
A88: 7.b | B88: Pembayaran, Wallet & Koin | C88: Halaman | D88: Wallet koin | E88: Selesai | F88: Tidak berubah sejak 15 Agu; tidak ditemukan masalah terbuka. | G88: https://saloka.id/wallet/coin | H88: Pengguna yang sudah login | I88: Saldo dan riwayat koin pribadi. | J88: Saldo & transaksi koin | K88: User (coinBalance), CoinTransaction | L88: coin.getUserCoinBalance, getCoinTransactionHistory | M88: src/app/wallet/coin/page.tsx | P88: 2026-06-25 | Q88: 2026-08-15
A89: 7.c | B89: Pembayaran, Wallet & Koin | C89: Halaman | D89: Pusat voucher | E89: Selesai | F89: Tidak berubah sejak 29 Agu; tidak ditemukan masalah terbuka. | G89: https://saloka.id/voucher | H89: Semua orang (klaim perlu login) | I89: Pusat voucher & promo; tukar koin dengan voucher. | J89: Voucher, penukaran | K89: CoinVoucher, CoinRedemption | L89: coin.getCoinVouchers, redeemCoinVoucher, getUserRedemptions | M89: src/app/voucher/VoucherClient.tsx | P89: 2026-08-15 | Q89: 2026-08-29
A90: 7.d | B90: Pembayaran, Wallet & Koin | C90: Alur | D90: Payment gateway DOKU | E90: Quality Check | F90: Live sejak 16 Sep (satu-satunya gateway); Midtrans dihapus dari kode. Webhook RSA-SHA256, cek status ke DOKU, dan idempotensi orderId terverifikasi 30 Sep. | G90: Dipakai oleh /cart, /wallet, bergabung komunitas / simpanan / top-up koin | H90: Sistem | I90: Checkout, QRIS / virtual account di dalam aplikasi, webhook dengan pengecekan signature RSA, verifikasi status; mencegah pengkreditan ganda. | J90: Status pembayaran untuk pesanan, deposit, biaya bergabung, simpanan, top-up koin | K90: Order, WalletTransaction, CoinTransaction, CooperativeSavingsTransaction | L90: /api/doku/checkout, /direct, /notification, /verify; /api/payment/checkout, /api/payment/verify | M90: src/lib/doku.ts; src/lib/payment-gateway.ts; src/lib/payment-purposes.ts | N90: Minggu C (14–20 Sep) | O90: Rekonsiliasi settlement terjadwal belum ada (satu-satunya cron: purge-audit-logs); refund pesanan berbayar masih manual. | P90: 2026-09-12 | Q90: 2026-09-13 | AF90: 1. Autentikasi DOKU gagal 2. Pembayaran ditandai lunas sebelum dikonfirmasi DOKU 3. Route DOKU mengizinkan panggilan tanpa autentikasi untuk melunasi pembayaran | AG90: 1. — 2. — 3. — | AH90: 1. Bearer API key dengan fallback HMAC (e9985f3) 2. Cek status DOKU sebelum pelunasan (0b61de7) 3. Celah ditutup (484e593) | AI90: 1. 2026-09-12 2. 2026-09-12 3. 2026-09-13
A91: 7.e | B91: Pembayaran, Wallet & Koin | C91: Alur | D91: Pengiriman Biteship | E91: Sedang Berjalan | F91: Area & tarif berjalan sejak 12 Sep; fallback Komerce sudah dihapus. Pelacakan otomatis belum ada (diverifikasi 30 Sep). | G91: Dipakai oleh /cart | H91: Sistem | I91: Pencarian tujuan dan tarif kurir. | J91: Area & tarif pengiriman | L91: /api/shipping/destination, /api/shipping/calculate | M91: src/lib/biteship.ts; src/lib/komerce.ts | N91: Minggu C | O91: trackBiteshipWaybill tidak dipanggil dari mana pun; tidak ada webhook Biteship dan tidak ada pembuatan pesanan kurir (booking) via API. | P91: 2026-09-12 | Q91: 2026-09-12 | AF91: Request tarif kurir ditolak (parameter couriers tidak ada) | AG91: — | AH91: Parameter ditambahkan (8d3d7fd) | AI91: 2026-09-12
A92: 7.f | B92: Pembayaran, Wallet & Koin | C92: Halaman Admin | D92: Admin · Transaksi | E92: Quality Check | F92: CMS direstrukturisasi 5 Sep. | G92: https://saloka.id/cms_admin/transactions | H92: Admin dengan izin “transactions” | I92: Riwayat transaksi marketplace dan jasa. | J92: Pesanan | K92: Order | L92: admin.trackTransactionAction | M92: src/app/cms_admin/components/TransactionsTab.tsx | N92: Minggu C | P92: 2026-09-05 | Q92: 2026-09-05
A93: 7.g | B93: Pembayaran, Wallet & Koin | C93: Halaman Admin | D93: Admin · Withdrawal | E93: Quality Check | F93: CMS direstrukturisasi 5 Sep. | G93: https://saloka.id/cms_admin/withdrawals | H93: Admin dengan izin “withdrawals” | I93: Memproses permintaan penarikan dana merchant & affiliate. | J93: Permintaan penarikan | K93: Wallet, WalletTransaction | M93: src/app/cms_admin/components/WithdrawalsTab.tsx | P93: 2026-09-05 | Q93: 2026-09-05
A94: 7.h | B94: Pembayaran, Wallet & Koin | C94: Halaman Admin | D94: Admin · Koin & Voucher | E94: Quality Check | F94: Angka supply diperbaiki 15 Agu; CMS direstrukturisasi 5 Sep. | G94: https://saloka.id/cms_admin/coins/supply | H94: Admin dengan izin “coins” | I94: Supply koin, pemegang koin, voucher, dan ledger. | K94: CoinSystemConfig, CoinSupplyLog, CoinTransaction, CoinVoucher | M94: src/app/cms_admin/components/CoinsTab.tsx | P94: 2026-09-05 | Q94: 2026-09-05
A95: 7.h.i | B95: Pembayaran, Wallet & Koin | C95: Tab Admin | D95: Supply & Distribusi | E95: Quality Check | F95: Data asli. | G95: https://saloka.id/cms_admin/coins/supply | I95: Atur total supply dan distribusikan koin. | L95: coin.getCoinSupplyConfigAction, updateCoinSupplyAction, distributeCoinFromSupplyAction | T95: Supply koin beredar/tersedia salah; supply komunitas tidak berkurang saat alokasi | U95: — | V95: Total real-time; pengurangan otomatis (2c93abb, bea6b01) | W95: 2026-08-15
A96: 7.h.ii | B96: Pembayaran, Wallet & Koin | C96: Tab Admin | D96: Pemegang Koin | E96: Quality Check | F96: Data asli. | G96: https://saloka.id/cms_admin/coins/holders | I96: Siapa saja pemegang koin; suntik koin. | L96: admin.getAllCoinHoldersAction, injectCoinAction
A97: 7.h.iii | B97: Pembayaran, Wallet & Koin | C97: Tab Admin | D97: Voucher | E97: Quality Check | F97: Data asli. | G97: https://saloka.id/cms_admin/coins/voucher | I97: Buat dan aktifkan/nonaktifkan voucher koin. | L97: coin.createCoinVoucherAdmin, toggleCoinVoucherActive
A98: 7.h.iv | B98: Pembayaran, Wallet & Koin | C98: Tab Admin | D98: Ledger | E98: Quality Check | F98: Data asli. | G98: https://saloka.id/cms_admin/coins/ledger | I98: Log supply koin. | L98: coin.getCoinSupplyLogsAction
A99: 7.i | B99: Pembayaran, Wallet & Koin | C99: Halaman Admin | D99: Admin · Metode Pembayaran | E99: Quality Check | F99: Dibuat 8 Agu; perannya di samping DOKU perlu dikonfirmasi. | G99: https://saloka.id/cms_admin/payment-methods | H99: Admin dengan izin “payment-methods” | I99: Rekening bank manual dan QRIS yang ditawarkan saat checkout. | J99: Metode pembayaran | K99: PaymentMethod | L99: /api/admin/payment-methods | M99: src/app/cms_admin/components/PaymentMethodsTab.tsx | P99: 2026-08-08 | Q99: 2026-09-05
A100: 8 | B100: Alat Merchant & Storefront | C100: Fitur | D100: Alat Merchant & Storefront | E100: Quality Check | F100: Dashboard, builder, dan storefront berjalan; kustomisasi storefront hanya tersimpan di browser.
...

Sheet Panduan
A1: Cara membaca workbook ini
A2: Satu baris untuk setiap fitur (hijau), halaman, tab, layar admin (CMS), alur di balik layar, atau komponen di seluruh situs saloka.id. Disusun dari repository kode pada 13 Sep 2026.
A3: Gunakan filter di baris 2 sheet “Pelacak Fitur” (misalnya filter Fitur atau Status), atau tombol +/− di sisi kiri untuk menutup/membuka halaman dan tab.
A4: Status (dropdown di kolom E)
A5: Selesai — dibangun dengan data asli, tidak ditemukan kekurangan di kode, tidak ada perbaikan dalam 2 minggu terakhir.
A6: Quality Check — dibangun dengan data asli, tetapi baru diubah/diperbaiki atau masih menunggu persetujuan QA.
A7: Sedang Berjalan — baru sebagian dibangun, memakai data mock/contoh, atau masih ada bagian yang kurang.
A8: Belum Dimulai — hanya ada layar placeholder (misalnya “Segera Hadir”).
A9: Status disimpulkan dari kode, riwayat commit, roadmap September 2026, dan catatan progres mingguan — bukan dari pengujian langsung di situs. Mohon ditinjau, dengan melihat kolom “Alasan status”.
A10: Level
A11: Fitur → Halaman / Halaman Admin / Alur / Komponen → Tab / Tab Admin. Alur = proses di balik layar tanpa halaman sendiri (misalnya pembayaran DOKU). Komponen = elemen yang tampil di seluruh situs (misalnya kolom pencarian).
A12: Baris Komunitas menyebutkan tipe komunitas (Perkumpulan atau Koperasi) serta tier atau template yang berlaku di kolom “Siapa yang bisa akses”.
... A23: “Phase 6” merujuk pada pekerjaan komunitas yang ditunda (pencairan pinjaman, transfer SHU ke wallet, penagihan tier, dll.) yang tercantum di PHASE6_TODO.md.
